autora/experimentalist/sampler/nearest_value/__init__.py
autora_experimentalist_sampler_nearest_value-1.0.1.dist-info/METADATA
autora_experimentalist_sampler_nearest_value-1.0.1.dist-info/WHEEL
autora_experimentalist_sampler_nearest_value-1.0.1.dist-info/top_level.txt
autora_experimentalist_sampler_nearest_value-1.0.1.dist-info/RECORD
