Metadata-Version: 2.1
Name: autora-experimentalist-sampler-nearest-value
Version: 1.0.1
Summary: A sampler which returns the nearest values between the input samples and the allowed values, without replacement.
Author-email: "Built by Sebastian Musslick, restructured by Chad Williams" <sebastian_musslick@brown.edu>
License: MIT license
Project-URL: homepage, http://www.empiricalresearch.ai
Project-URL: repository, https://github.com/AutoResearch/autora-experimentalist-sampler-nearest-value
Project-URL: documentation, https://autoresearch.github.io/autora/
Requires-Python: <4,>=3.8
Requires-Dist: autora-core
Requires-Dist: scikit-learn
Provides-Extra: dev
Requires-Dist: autora-core[dev] ; extra == 'dev'
